DeskPerformance/__init__.py
DeskPerformance/pf.py
pc_metrics_collector-0.3.dist-info/METADATA
pc_metrics_collector-0.3.dist-info/WHEEL
pc_metrics_collector-0.3.dist-info/entry_points.txt
pc_metrics_collector-0.3.dist-info/top_level.txt
pc_metrics_collector-0.3.dist-info/RECORD
