Metadata-Version: 2.1
Name: pc_metrics_collector
Version: 0.3
Requires-Dist: psutil
Requires-Dist: websockets
Requires-Dist: click
